Python_RESTArt-0.1.6.dist-info/DESCRIPTION.rst
Python_RESTArt-0.1.6.dist-info/METADATA
Python_RESTArt-0.1.6.dist-info/RECORD
Python_RESTArt-0.1.6.dist-info/WHEEL
Python_RESTArt-0.1.6.dist-info/entry_points.txt
Python_RESTArt-0.1.6.dist-info/metadata.json
Python_RESTArt-0.1.6.dist-info/top_level.txt
restart/__init__.py
restart/adapter.py
restart/api.py
restart/cli.py
restart/exceptions.py
restart/logging.py
restart/negotiator.py
restart/parsers.py
restart/renderers.py
restart/request.py
restart/resource.py
restart/response.py
restart/serving.py
restart/status.py
restart/testing.py
restart/utils.py
restart/config/__init__.py
restart/config/default.py
restart/ext/__init__.py
