Metadata-Version: 2.0
Name: Python-RESTArt
Version: 0.1.6
Summary: A Python library with good intentions for building REST APIs.
Home-page: https://github.com/RussellLuo/restart
Author: RussellLuo
Author-email: luopeng.he@gmail.com
License: MIT
Keywords: REST APIs,Python
Platform: UNKNOWN
Requires-Dist: Werkzeug (>=0.9)
Requires-Dist: click (>=4.0)
Requires-Dist: python-easyconfig (>=0.1.6)
Requires-Dist: six (>=1.9.0)
